Workbook

Sheet Hypotheses
A1: ID | B1: Theme | C1: Plain-English question | D1: Formal hypothesis (as tested) | E1: Methodology | F1: Finding (numbers) | G1: Verdict | H1: Assumptions and caveats | I1: What would break this | J1: Policy meaning | K1: Where used | L1: Source script
A2: EH1 | B2: 1. Is the grade 6 decline real? | C2: Does the grade 6 collapse survive if we only look at places that took part every year? | D2: G6 multiplicative decline survives inside a constant-GP panel (same GPs all 3 years) | E2: Kept only the Gram Panchayats that fielded at least 10 grade 6 children in all three years (2,182 GPs). Compared their 2022-23 and 2024-25 competency scores, student-weighted. If new weaker places caused the fall, it should shrink or vanish here. | F2: panel (k=2182 GPs): mult 50.5->30.8 (-19.7pp vs raw -15.8pp, 125% persists); div 54.5->32.5 (-22.0pp vs raw -17.4pp, 127% persists) | G2: SUPPORTED | H2: Panel GPs are early joiners, so better organised on average. That bias would flatter the trend, not worsen it. Items change yearly, so comparison is at competency level. || Pipeline caveat: items change each year; competency-level comparison assumes similar within-competency difficulty; panel GPs are earlier joiners, not a random subset | I2: If the 2,182 panel GPs were unrepresentative in a way that inflates decline, e.g. all from one collapsing region. Check: rerun by revenue division. | J2: If it survives, the G6 collapse is real deterioration, not new-GP composition; remediation, not measurement, is the response. | K2: Report 4.0 (lead finding) | Slide 4 | Policy note para 1 | L2: src/extra_hypotheses.py
A3: EH3 | B3: 1. Is the grade 6 decline real? | C3: Does the decline show up in districts where coverage barely moved? | D3: G6 decline present even in districts whose coverage changed least | E3: Ranked districts by absolute change in coverage 2022-23 to 2024-25, took the bottom third (8 districts, mean change 3.9pp), and measured their grade 6 competency change. | F3: bottom-tercile |d_cov| (8 districts, mean |d_cov|=3.9pp): mult -18.7pp, div -21.4pp (all-district: -20.1/-22.6) | G3: SUPPORTED | H3: Unweighted district means. District-level coverage stability does not guarantee stability of reach within the district. || Pipeline caveat: coverage change is district-level; within-district reach can still shift | I3: Only 8 districts, so noisy. But EH1 and EH6 use different logic and land in the same range. | J3: Decline without a coverage story in these districts undercuts the pure-selection explanation. | K3: Report 4.0 | Slide 4 | L3: src/extra_hypotheses.py
A4: EH5 | B4: 1. Is the grade 6 decline real? | C4: If you statistically remove coverage change, how much decline is left? | D4: A G6 multiplication decline remains after controlling district coverage change | E4: District-level OLS: regressed change in grade 6 multiplication on change in coverage, then read the intercept, i.e. the predicted decline for a district whose coverage did not move. | F4: regression d(mult) = -19.32 -0.03*d_cov (n=25); predicted decline at zero coverage change: -19.3pp (raw mean -20.1pp, sd 4.1) | G4: SUPPORTED | H4: Linear control only, at district level. Selection happening school by school inside a district is invisible to this test. || Pipeline caveat: linear control only; unmeasured within-district selection can remain | I4: A strongly non-linear coverage effect. EH1 handles the within-district case a different way. | J4: The coverage-free decline estimate is the honest headline number for the G6 collapse. | K4: Report 4.0 | claims.json claim-eh5-intercept | L4: src/extra_hypotheses.py
A5: EH6 | B5: 1. Is the grade 6 decline real? | C5: Does the decline appear in districts that were already deeply covered from the start? | D5: G6 decline appears even in districts already deeply covered in 2022-23 (>=40%) | E5: Selected the 11 districts already at 40% coverage or higher in 2022-23. These had least room for composition to dilute the average, since most eligible children were already in. | F5: 11 districts with 2022-23 coverage >=40%: mult -19.8pp, div -21.7pp | G5: SUPPORTED | H5: Small n. Deep-start districts may differ in administrative capacity or geography. || Pipeline caveat: small n; deep-start districts may differ in other ways | I5: If deep-start districts share a confound that drives decline independently. Four designs now agree within 18-22pp. | J5: Same conclusion as EH1 by a different route; two independent designs agreeing is strong evidence. | K5: Report 4.0 | Slide 4 | L5: src/extra_hypotheses.py
A6: EH2 | B6: 1. Is the grade 6 decline real? | C6: Does the one piece of good news, grade 4 division improving, also survive? | D6: G4 division improvement survives inside the constant-GP panel | E6: Identical constant-GP panel construction as EH1, applied to grade 4 division (2,278 GPs). | F6: panel (k=2278 GPs): G4 div 39.0->38.4 (-0.6pp vs raw +5.6pp) | G6: DISCARD | H6: Same panel caveats as EH1. The raw gain and the panel result use the same competency mapping. || Pipeline caveat: items change each year; competency-level comparison assumes similar within-competency difficulty | I6: Nothing visible. Two panels built identically gave opposite answers about their own headlines, which is the test working. | J6: A real G4 gain alongside a real G6 loss points at the upper-primary transition, not at a cohort-wide shock. | K6: Report 4.0 and section 5 | Slide 4 | Killed our own good news | L6: src/extra_hypotheses.py
A7: EH4 | B7: 1. Is the grade 6 decline real? | C7: Do the districts that expanded coverage most show the biggest score falls? | D7: Districts that widened coverage most saw scores fall most (selection story) | E7: Correlated each district's change in coverage against its change in mean score, 2022-23 to 2024-25, rural State Government basis on both sides. This is the selection story's own preferred test. | F7: r=-0.18 (p=0.396, n=25 districts); slope -0.33pp score per +10pp coverage | G7: DISCARD | H7: Ecological correlation at district level. Coverage growth also tracks administrative effort, which could push the other way. || Pipeline caveat: ecological correlation; district coverage growth also tracks admin effort | I7: Only 25 districts, so a small effect could hide. But we are asking whether it explains a 16pp fall, and it does not. | J7: If supported, part of the reported decline is the contest reaching weaker children, which is a participation success, not only a learning failure. | K7: Report 4.0 and section 5 | Slide 4 | Kills the selection story | L7: src/extra_hypotheses.py
A8: EH22 | B8: 1. Is the grade 6 decline real? | C8: Do the newly reached places actually have weaker children? | D8: GPs newly reached in 2024-25 score below veteran GPs (direct composition evidence) | E8: Identified the 655 GPs that first appear in 2024-25, compared their grade 6 mean against veteran GPs. This tests the unstated assumption the entire selection story rests on. | F8: new GPs (k=655, 16% of G6 students): mean 53.1 vs veteran GPs 48.6 (gap +4.6pp) | G8: DISCARD | H8: New GPs may be smaller or may have sent only their strongest children on a first outing. Either way it is not evidence for the selection story. || Pipeline caveat: new GPs may differ in remoteness and size, not only preparedness | I8: First-outing selection within new GPs. Even so, the selection story requires new places to score lower, and they score higher. | J8: Quantifies exactly how much of the 'decline' is the contest finding weaker children. Pair with EH1 for the full story. | K8: Report 4.0 and section 5 | Selection story runs backwards | L8: src/extra_hypotheses.py
A9: H9 | B9: 1. Is the grade 6 decline real? | C9: Can we test who-got-tested bias by joining GP names to UDISE? | D9: Who-got-tested bias | E9: Attempted a GP-name join to UDISE enrolment to compare tested against enrolled children at GP level. An automatic reliability gate refused the join. | F9: join too thin | G9: DISCARD | H9: GP names repeat across districts and the fuzzy match reached only 37%, below the 60% usable threshold. || Pipeline caveat: expected fuzziness materialised | I9: Not fixable with available data. We answered the same question better at district level, in EH1 to EH6 and EH22. | J9: Fall back to district-level coverage in the afternoon if time allows. | K9: Report 6b | Shows exactly where our data runs out | L9: src/day1_verdicts.py
A10: EH8 | B10: 2. Is the girls' lead real? | C10: Where more girls are tested than boys, is the girls' measured lead bigger? | D10: Where girls are over-assessed relative to boys, the girls' score lead is larger (participation, not learning) | E10: For each district-year, computed the girls-minus-boys gap in assessment coverage (verified UDISE rural State Govt denominator) and the girls-minus-boys gap in score, then correlated the two across 80 district-years. | F10: r=0.47 (p=1.14e-05, n=80 district-years) between (girls-boys coverage) and (girls-boys score) | G10: SUPPORTED | H10: District-level. Selection happening within a school is unobserved. || Pipeline caveat: district-level; within-school selection unobserved | I10: Nothing. This finding cuts against us and we report it as a caution on district gender gaps. | J10: If near zero, the girls' lead looks like learning, not who showed up. | K10: Report 4.5 | Slide 7 | Forces coverage next to every district gender gap | L10: src/extra_hypotheses.py
A11: EH9 | B11: 2. Is the girls' lead real? | C11: Do girls still lead where boys and girls are tested at equal rates? | D11: Girls still lead in districts where boys and girls are assessed at near-equal rates (|coverage gap|<=2pp) | E11: Restricted to the 25 district-years where the boy-girl coverage gap is within 2pp, then recomputed the score gap. If the lead is a participation mirage it should shrink here. | F11: balanced district-years (n=25): girls-boys score gap +3.57pp (all: +2.79pp) | G11: SUPPORTED | H11: Balance is defined at district level on the verified UDISE denominator. It does not guarantee balance in every school. Sample shrinks under the filter. || Pipeline caveat: n shrinks under the balance filter | I11: If the 25 balanced district-years are systematically high-performing. Check: compare their mean score against the state mean. | J11: A gap that survives balance is a real learning lead; report it with Cohen's d, not p-values. | K11: Report 4.5 | Slide 7 | claims.json claim-eh9-genderbal | L11: src/extra_hypotheses.py
A12: EH10 | B12: 2. Is the girls' lead real? | C12: Is the girls' lead steady over time while coverage doubled? | D12: The girls' lead is stable across the three contest years despite coverage doubling | E12: Computed the mean district-level girls-minus-boys gap separately for each of the three years. A participation artefact should wobble as participation changes. | F12: girls-boys gap by year: 2022-23 +3.17pp, 2023-24 +2.55pp, 2024-25 +2.62pp | G12: SUPPORTED | H12: Unweighted mean of district gaps. Items change yearly. || Pipeline caveat: items change each year; competency-level comparison assumes similar within-competency difficulty | I12: A coincidence where two opposing changes cancel out across three years. Unlikely. | J12: Stability across a doubling of reach argues the lead is not a participation artefact. | K12: Report 4.5 | Slide 7 | L12: src/extra_hypotheses.py
... A37: H10 | B37: 6. Geography, history and money | C37: Do government schools score worse where private schools are common? | D37: High private-school presence, lower government-school scores (selection) | E37: Correlated the share of private schools in a block against block mean government-school score, testing whether private schools cream off advantaged children. | F37: r=-0.14 (p=0.133, n=116 blocks) | G37: DISCARD | H37: This is a composition and selection story, not a measure of school quality. Block join is 68%. || Pipeline caveat: composition/selection story, not school quality; CMS-E shows exit is income-graded | I37: r = -0.14, p = 0.13. Direction is plausible but the evidence is not there at this sample size. | J37: Do not present. If asked, say it was tested and found near-zero. | K37: Report section 5 | L37: src/day1_verdicts.py

Sheet Summary
A1: Hypothesis register: summary
A2: Counts recalculate from the Hypotheses tab. Source of every number: outputs/tables/hypothesis_menu.csv, produced by src/run_all.py then src/day1_verdicts.py then src/extra_hypotheses.py (seed 20260801).
A4: Verdict | B4: Count | C4: Share of all | D4: What it means
A5: SUPPORTED | B5: =COUNTIF(Hypotheses!$G$2:$G$37,A5) -> 20 | C5: =B5/$B$8 -> 0.55555556 | D5: Effect is sizeable, unlikely to be chance, and survived a test built to break it. Safe to present.
A6: WEAK | B6: =COUNTIF(Hypotheses!$G$2:$G$37,A6) -> 3 | C6: =B6/$B$8 -> 0.083333333 | D6: Visible but small, or failed one check. Mention with the caveat; do not build a slide on it.
A7: DISCARD | B7: =COUNTIF(Hypotheses!$G$2:$G$37,A7) -> 13 | C7: =B7/$B$8 -> 0.36111111 | D7: No usable signal, or the test could not be run. Reported openly in report.pdf section 5.
A8: TOTAL | B8: =SUM(B5:B7) -> 36 | C8: =B8/$B$8 -> 1
A10: By theme
A11: Theme | B11: Total | C11: Supported | D11: Weak | E11: Discarded
A12: 1. Is the grade 6 decline real? | B12: =COUNTIF(Hypotheses!$B$2:$B$37,$A12) -> 8 | C12: =COUNTIFS(Hypotheses!$B$2:$B$37,$A12,Hypotheses!$G$2:$G$37,"SUPPORTED") -> 4 | D12: =COUNTIFS(Hypotheses!$B$2:$B$37,$A12,Hypotheses!$G$2:$G$37,"WEAK") -> 0 | E12: =COUNTIFS(Hypotheses!$B$2:$B$37,$A12,Hypotheses!$G$2:$G$37,"DISCARD") -> 4
A13: 2. Is the girls' lead real? | B13: =COUNTIF(Hypotheses!$B$2:$B$37,$A13) -> 6 | C13: =COUNTIFS(Hypotheses!$B$2:$B$37,$A13,Hypotheses!$G$2:$G$37,"SUPPORTED") -> 3 | D13: =COUNTIFS(Hypotheses!$B$2:$B$37,$A13,Hypotheses!$G$2:$G$37,"WEAK") -> 2 | E13: =COUNTIFS(Hypotheses!$B$2:$B$37,$A13,Hypotheses!$G$2:$G$37,"DISCARD") -> 1
A14: 3. Can we trust the instrument? | B14: =COUNTIF(Hypotheses!$B$2:$B$37,$A14) -> 4 | C14: =COUNTIFS(Hypotheses!$B$2:$B$37,$A14,Hypotheses!$G$2:$G$37,"SUPPORTED") -> 1 | D14: =COUNTIFS(Hypotheses!$B$2:$B$37,$A14,Hypotheses!$G$2:$G$37,"WEAK") -> 1 | E14: =COUNTIFS(Hypotheses!$B$2:$B$37,$A14,Hypotheses!$G$2:$G$37,"DISCARD") -> 2
A15: 4. Averages and league tables mislead | B15: =COUNTIF(Hypotheses!$B$2:$B$37,$A15) -> 6 | C15: =COUNTIFS(Hypotheses!$B$2:$B$37,$A15,Hypotheses!$G$2:$G$37,"SUPPORTED") -> 6 | D15: =COUNTIFS(Hypotheses!$B$2:$B$37,$A15,Hypotheses!$G$2:$G$37,"WEAK") -> 0 | E15: =COUNTIFS(Hypotheses!$B$2:$B$37,$A15,Hypotheses!$G$2:$G$37,"DISCARD") -> 0
A16: 5. Where in maths do children fall off? | B16: =COUNTIF(Hypotheses!$B$2:$B$37,$A16) -> 2 | C16: =COUNTIFS(Hypotheses!$B$2:$B$37,$A16,Hypotheses!$G$2:$G$37,"SUPPORTED") -> 2 | D16: =COUNTIFS(Hypotheses!$B$2:$B$37,$A16,Hypotheses!$G$2:$G$37,"WEAK") -> 0 | E16: =COUNTIFS(Hypotheses!$B$2:$B$37,$A16,Hypotheses!$G$2:$G$37,"DISCARD") -> 0
A17: 6. Geography, history and money | B17: =COUNTIF(Hypotheses!$B$2:$B$37,$A17) -> 10 | C17: =COUNTIFS(Hypotheses!$B$2:$B$37,$A17,Hypotheses!$G$2:$G$37,"SUPPORTED") -> 4 | D17: =COUNTIFS(Hypotheses!$B$2:$B$37,$A17,Hypotheses!$G$2:$G$37,"WEAK") -> 0 | E17: =COUNTIFS(Hypotheses!$B$2:$B$37,$A17,Hypotheses!$G$2:$G$37,"DISCARD") -> 6

Sheet How to read this
A1: How to read this register
A3: What this file is | B3: Every hypothesis we tested on the Akshara GP Maths Contest data, whether it survived or not. 36 in total. Testing in public is deliberate: a question answered honestly and discarded is worth more than a question avoided.
A4: Where the numbers come from | B4: The Finding, Verdict, formal hypothesis text and pipeline caveat are read directly from outputs/tables/hypothesis_menu.csv by src/build_hypothesis_xlsx.py. They are not retyped by hand. The plain-English question, methodology, assumptions and break-conditions are written by the team.
A5: How to reproduce | B5: From the repo root: python src/run_all.py, then python src/day1_verdicts.py, then python src/extra_hypotheses.py. Fixed seed 20260801. Runs offline in about three minutes.
A6: Verdict thresholds | B6: SUPPORTED needs a sizeable effect, statistical clarity, and survival of a robustness check. WEAK means small, or one check failed. DISCARD means no usable signal or the test could not be run. Thresholds are stated in the docstring of each source script so a judge can check them.
A7: Causal language | B7: This is observational data. Every judgment in the report is phrased as consistent-with. Nothing here proves causation, and nothing claims to.
A8: The cross-year caveat | B8: The 20 questions change every year within a constant competency framework. All cross-year statements are made at competency or ranking level, never as raw item-score gains, and the headline decline is corroborated by two independent external assessments (ASER 2024 and PARAKH RS 2024).
A9: The universe | B9: Rural State Government schools only, grades 4 to 6, 1,379,087 student records across three years. Every UDISE denominator filters to management_group = State Government and rural_urban = Rural. This makes ASER, which is also rural-only, a like-for-like benchmark.
A10: Known weaknesses we would raise ourselves | B10: EH13 names division as the best single proxy at 0.67, but measurement is also 0.67 and multiplication 0.66; the honest phrasing is that the multiplicative family carries most information. EH15's correlation of -0.62 is inflated by a ceiling effect; the direction holds, the magnitude does not.
